fontgen/__init__.py
fontgen/__main__.py
fontgen/matrai_generator_1.py
fontgen/matrai_generator_2.py
fontgen/matrai_generator_2_suffix.py
fontgen/matrai_generator_3.py
fontgen/setFilters.py
fontgen/config/__init__.py
fontgen/config/config.ini
fontgen/config/fontshare.ini
fontgen/config/itf.ini
fontgen/config/setconfig.py
fontgen/config/test.ini
fontgen/filters/__init__.py
fontgen/filters/fontinfo_fix.py
fontgen/filters/matrai_gen.py
fontgen/filters/matrai_sub.py
fontgen/filters/unicode_fix.py
fontgen/filters/variable_tag.py
fontgen-0.0.4.dist-info/LICENSE
fontgen-0.0.4.dist-info/METADATA
fontgen-0.0.4.dist-info/WHEEL
fontgen-0.0.4.dist-info/entry_points.txt
fontgen-0.0.4.dist-info/top_level.txt
fontgen-0.0.4.dist-info/RECORD
