Metadata-Version: 2.1
Name: fontgen
Version: 0.0.4
Summary: Python package for generating fonts
Home-page: https://github.com/itfoundry/fontgen
Author: Rahul Gajjar
Author-email: rahulgajjar20@gmail.com
License: UNKNOWN
Platform: UNKNOWN
Classifier: Development Status :: 1 - Planning
Classifier: Programming Language :: Python :: 3.9
Classifier: Operating System :: OS Independent
Requires-Python: >=3.6
Requires-Dist: fontmake
Requires-Dist: fontParts
